pyforensickit/__init__.py
pyforensickit/cli/main.py
pyforensickit/core/case.py
pyforensickit/core/hashing.py
pyforensickit/core/metadata.py
pyforensickit/core/report.py
pyforensickit/core/timeline.py
pyforensickit/utils/filesystem.py
pyforensickit-0.1.1.dist-info/licenses/LICENSE
pyforensickit-0.1.1.dist-info/METADATA
pyforensickit-0.1.1.dist-info/WHEEL
pyforensickit-0.1.1.dist-info/entry_points.txt
pyforensickit-0.1.1.dist-info/top_level.txt
pyforensickit-0.1.1.dist-info/RECORD
