Metadata-Version: 2.4
Name: pyforensickit
Version: 0.1.1
Summary: Linux-based digital forensics command-line toolkit
Author-email: Samuel Selasi <samelsekasi@gmail.com>
License: MIT
Requires-Python: >=3.10
License-File: LICENSE
Requires-Dist: rich>=13.0.0
Requires-Dist: python-magic>=0.4.27
Dynamic: license-file
